folder_tree_generator/__init__.py
folder_tree_generator/folder_tree_generator.py
folder_tree_generator/py.typed
folder_tree_generator-0.1.14.dist-info/LICENSE
folder_tree_generator-0.1.14.dist-info/METADATA
folder_tree_generator-0.1.14.dist-info/WHEEL
folder_tree_generator-0.1.14.dist-info/RECORD
