Metadata-Version: 2.1
Name: folder-tree-generator
Version: 0.1.14
Summary: Takes a folder path and outputs a text representation of the folders and files, supports ignore files.
Author: Sean Dearnaley
Author-email: SeanDearnaley@outlook.com
Requires-Python: >=3.10,<4.0
Classifier: Programming Language :: Python :: 3
Classifier: Programming Language :: Python :: 3.10
Classifier: Programming Language :: Python :: 3.11
